cpu/src/stack_pointer.v
module SP(
    input pop, push, reset, clk,
    output reg [15:0] out
);

    always @(posedge clk or posedge reset) begin
        if (reset)
            out <= 16'hFFFF;  // Reset value
        else if (push)
            out <= out - 1;  // Decrement SP on push
        else if (pop)
            out <= out + 1;  // Increment SP on pop
    end

endmodule

cpu/tests/stack_pointer_tb.v
`timescale 1ns / 1ps

module SP_tb();

    reg pop, push, reset, clk;
    wire [15:0] out;
    SP sp_instance(.pop(pop), .push(push), .reset(reset), .clk(clk), .out(out));

    // Clock generation
    always #10 clk = ~clk; // 50 MHz Clock

    // Initialize all inputs
    initial begin
        clk = 0;
        reset = 0;
        push = 0;
        pop = 0;

        // Dump VCD file
        $dumpfile("waveform.vcd");
        $dumpvars(0, SP_tb);


        // Reset the SP
        #20 reset = 1;
        #20 reset = 0;

        // Test push operations
        #20 push = 1;
        #20 push = 0;

        // Test pop operations
        #20 pop = 1;
        #20 pop = 0;

        // Testing with multiple pushes and pops
        #20 push = 1;
        #20 push = 0;
        #20 push = 1;
        #20 push = 1;
        #20 push = 1;
        #20 push = 0;
        #20 pop = 1;
        #20 pop = 0;


        // End simulation
        #100 $finish;
    end

    // Monitor changes
    initial begin
        $monitor("Time = %t, Reset = %b, Push = %b, Pop = %b, SP = %h", 
                  $time, reset, push, pop, out);
    end

endmodule

cpu/waveform.vcd
$date
	Sat Jan  6 01:09:44 2024
$end
$version
	Icarus Verilog
$end
$timescale
	1ps
$end
$scope module SP_tb $end
$var wire 16 ! out [15:0] $end
$var reg 1 " clk $end
$var reg 1 # pop $end
$var reg 1 $ push $end
$var reg 1 % reset $end
$scope module sp_instance $end
$var wire 1 " clk $end
$var wire 1 # pop $end
$var wire 1 $ push $end
$var wire 1 % reset $end
$var reg 16 & out [15:0] $end
$upscope $end
$upscope $end
$enddefinitions $end
$comment Show the parameter values. $end
$dumpall
$end
#0
$dumpvars
bx &
0%
0$
0#
0"
bx !
$end
#10000
1"
#20000
b1111111111111111 !
b1111111111111111 &
0"
1%
#30000
1"
#40000
0"
0%
#50000
1"
#60000
0"
1$
#70000
b1111111111111110 !
b1111111111111110 &
1"
#80000
0"
0$
#90000
1"
#100000
0"
1#
#110000
b1111111111111111 !
b1111111111111111 &
1"
#120000
0"
0#
#130000
1"
#140000
0"
1$
#150000
b1111111111111110 !
b1111111111111110 &
1"
#160000
0"
0$
#170000
1"
#180000
0"
1$
#190000
b1111111111111101 !
b1111111111111101 &
1"
#200000
0"
#210000
b1111111111111100 !
b1111111111111100 &
1"
#220000
0"
#230000
b1111111111111011 !
b1111111111111011 &
1"
#240000
0"
0$
#250000
1"
#260000
0"
1#
#270000
b1111111111111100 !
b1111111111111100 &
1"
#280000
0"
0#
